CHANGES.txt
CONTRIBUTORS.txt
MANIFEST.in
README.txt
setup.cfg
setup.py
plone/__init__.py
plone.recipe.apache.egg-info/PKG-INFO
plone.recipe.apache.egg-info/SOURCES.txt
plone.recipe.apache.egg-info/dependency_links.txt
plone.recipe.apache.egg-info/entry_points.txt
plone.recipe.apache.egg-info/namespace_packages.txt
plone.recipe.apache.egg-info/not-zip-safe
plone.recipe.apache.egg-info/requires.txt
plone.recipe.apache.egg-info/top_level.txt
plone/recipe/__init__.py
plone/recipe/apache/README.txt
plone/recipe/apache/__init__.py
plone/recipe/apache/build.py
plone/recipe/apache/building.txt
plone/recipe/apache/config.py
plone/recipe/apache/configuring.txt
plone/recipe/apache/doctests/technical_build.txt
plone/recipe/apache/doctests/technical_config.txt
plone/recipe/apache/templates/apache.conf.tmpl
plone/recipe/apache/templates/inner_vhost.conf.tmpl
plone/recipe/apache/templates/vhost.conf_tmpl
plone/recipe/apache/tests/__init__.py
plone/recipe/apache/tests/test_docs.py