Metadata-Version: 1.1
Name: plone.recipe.apache
Version: 0.3.3
Summary: An zc buildout for build and configure apache
Home-page: https://svn.plone.org/svn/collective/buildout/plone.recipe.apache
Author: Paris sprint 2008
Author-email: products-developers@lists.plone.org
License: ZPL
Keywords: plone recipe apache configure
Platform: UNKNOWN
Classifier: Framework :: Buildout
Classifier: Intended Audience :: Developers
Classifier: Topic :: Software Development :: Build Tools
Classifier: Topic :: Software Development :: Libraries :: Python Modules
Classifier: License :: OSI Approved :: Zope Public License
